pyczds/__init__.py
pyczds/authentication.py
pyczds/client.py
pyczds/helpers.py
pyCZDS-1.7.2.dist-info/LICENSE
pyCZDS-1.7.2.dist-info/METADATA
pyCZDS-1.7.2.dist-info/WHEEL
pyCZDS-1.7.2.dist-info/top_level.txt
pyCZDS-1.7.2.dist-info/RECORD
