Metadata-Version: 2.1
Name: pyCZDS
Version: 1.7.2
Summary: An API client for ICANN's Centralized Zone Data Service (CZDS). Learn more under https://czds.icann.org/.
Author-email: "Max M. Diez" <pyczds@xdiez.com>
Project-URL: Homepage, https://github.com/mdiez/pyCZDS
Project-URL: Bug Tracker, https://github.com/mdiez/pyCZDS/issues
Classifier: Programming Language :: Python :: 3
Classifier: License :: OSI Approved :: GNU General Public License v3 or later (GPLv3+)
Classifier: Operating System :: OS Independent
Classifier: Development Status :: 5 - Production/Stable
Classifier: Intended Audience :: Developers
Classifier: Topic :: Internet :: Name Service (DNS)
Classifier: Topic :: Software Development :: Libraries
Requires-Python: >=3.7
License-File: LICENSE
